LICENSE
NOTICE.md
progress/.DS_Store
progress/__init__.py
progress/__main__.py
progress/App/.DS_Store
progress/App/__init__.py
progress/App/about/__init__.py
progress/App/about/about_md.py
progress/App/api/__init__.py
progress/App/api/api_page.py
progress/App/api/ui/__init__.py
progress/App/api/ui/api_gui.ui
progress/App/api/ui/ui_api_gui.py
progress/App/gui_tools/__init__.py
progress/App/gui_tools/tools.py
progress/App/landing/__init__.py
progress/App/landing/landing_page.py
progress/App/landing/ui/__init__.py
progress/App/landing/ui/landing.ui
progress/App/landing/ui/ui_landing.py
progress/App/main_window/__init__.py
progress/App/main_window/mainwindow.ui
progress/App/main_window/ui_mainwindow.py
progress/App/results/__init__.py
progress/App/results/drag_widget.py
progress/App/results/results_view.py
progress/App/results/ui/__init__.py
progress/App/results/ui/results_viewer.ui
progress/App/results/ui/ui_results_viewer.py
progress/App/simulation/.DS_Store
progress/App/simulation/__init__.py
progress/App/simulation/sim_page.py
progress/App/simulation/ui/__init__.py
progress/App/simulation/ui/sim_gui.ui
progress/App/simulation/ui/ui_sim_gui.py
progress/App/solar/.DS_Store
progress/App/solar/__init__.py
progress/App/solar/solar_page.py
progress/App/solar/ui/__init__.py
progress/App/solar/ui/solar_gui.ui
progress/App/solar/ui/ui_solar_gui.py
progress/App/theme/__init__.py
progress/App/theme/dark.qss
progress/App/theme/light.qss
progress/App/wind/__init__.py
progress/App/wind/ui/__init__.py
progress/App/wind/ui/ui_wind_gui.py
progress/App/wind/ui/wind_gui.ui
progress/App/wind/wind_page.py
progress/Data/.DS_Store
progress/Data/Solar/solar_data.xlsx
progress/Data/Solar/solar_sites.csv
progress/Data/Solar/solardata/1998/101_PV_1.csv
progress/Data/Solar/solardata/1998/101_PV_1_sgen_cs.csv
progress/Data/Solar/solardata/1998/101_PV_1_sgen_sat.csv
progress/Data/Solar/solardata/1998/101_PV_2.csv
progress/Data/Solar/solardata/1998/101_PV_2_sgen_cs.csv
snl_progress-1.2.0.dist-info/entry_points.txt
snl_progress-1.2.0.dist-info/LICENSE
snl_progress-1.2.0.dist-info/METADATA
snl_progress-1.2.0.dist-info/NOTICE.md
snl_progress-1.2.0.dist-info/WHEEL
snl_progress-1.2.0.dist-info/RECORD
