Metadata-Version: 2.3
Name: snl-progress
Version: 1.2.0
Summary: Used to evaluate the reliability of a power system…
License: BSD-3-Clause
Author: Atri Bera
Author-email: abera@sandia.gov
Requires-Python: >=3.7,<3.12
Classifier: License :: OSI Approved :: BSD License
Classifier: Programming Language :: Python :: 3
Classifier: Programming Language :: Python :: 3.7
Classifier: Programming Language :: Python :: 3.8
Classifier: Programming Language :: Python :: 3.9
Classifier: Programming Language :: Python :: 3.10
Classifier: Programming Language :: Python :: 3.11
Requires-Dist: Markdown (==3.7)
Requires-Dist: NREL-rex (==0.2.86)
Requires-Dist: PySide6 (==6.5.2)
Requires-Dist: PySide6-Addons (==6.5.2)
Requires-Dist: PySide6-Essentials (==6.5.2)
Requires-Dist: kaleido (==0.2.1)
Requires-Dist: kneed (==0.8.5)
Requires-Dist: matplotlib (==3.9.0)
Requires-Dist: numpy (>=1.21.0,<2.0.0)
Requires-Dist: openpyxl (==3.1.4)
Requires-Dist: pandas (==2.2.2)
Requires-Dist: plotly (==5.22.0)
Requires-Dist: pvlib (==0.11.0)
Requires-Dist: pyomo (==6.7.3)
Requires-Dist: requests (==2.32.4)
Requires-Dist: scikit-learn (==1.5.0)
Requires-Dist: seaborn (==0.13.2)
Project-URL: Documentation, https://sandialabs.github.io/snl-progress/index.html
Project-URL: Homepage, https://github.com/sandialabs/snl-progress
Project-URL: Repository, https://github.com/sandialabs/snl-progress
